README.md
setup.py
jhxxr/__init__.py
jhxxr/test.py
jhxxr/timel.py
jhxxr.egg-info/PKG-INFO
jhxxr.egg-info/SOURCES.txt
jhxxr.egg-info/dependency_links.txt
jhxxr.egg-info/top_level.txt