Metadata-Version: 2.1
Name: jhxxr
Version: 0.0.4
Summary: Simple test example
Home-page: https://github.com/jhxxr/pip.git
Author: jhx
Author-email: 2471717907@qq.com
Classifier: Programming Language :: Python :: 3
Classifier: License :: OSI Approved :: MIT License
Classifier: Operating System :: OS Independent
Requires-Python: >=3.6
